[{
  "id": 1,
  "userName": "shiran",
  "name": "shiran",
  "q1": "a4",
  "q2": "a2",
  "q3": "a2",
  "q4": "a1"
}, {
  "id": 2,
  "userName": "liron",
  "name": "liron",
  "q1": "a4",
  "q2": "a2",
  "q3": "a2",
  "q4": "a1"
}, {
  "id": 3,
  "userName": "tal",
  "name": "tal",
  "q1": "a4",
  "q2": "a2",
  "q3": "a2",
  "q4": "a1"
}, {
  "id": 4,
  "userName": "gal",
  "name": "gal",
  "q1": "a4",
  "q2": "a2",
  "q3": "a2",
  "q4": "a1"
}, {
  "id": 5,
  "userName": "liraz",
  "name": "liraz",
  "q1": "a4",
  "q2": "a2",
  "q3": "a2",
  "q4": "a1"
}, {
  "id": 6,
  "userName": "avior",
  "name": "avior",
  "q1": "a4",
  "q2": "a2",
  "q3": "a2",
  "q4": "a1"
}, {
  "id": 7,
  "userName": "moran",
  "name": "moran",
  "q1": "a4",
  "q2": "a2",
  "q3": "a2",
  "q4": "a1"
}]